qsmxt/__init__.py
qsmxt/aseg_labels.csv
qsmxt/qsm_pipelines.json
qsmxt/cli/__init__.py
qsmxt/cli/dicom_convert.py
qsmxt/cli/dicom_sort.py
qsmxt/cli/main.py
qsmxt/cli/nifti_convert.py
qsmxt/interfaces/__init__.py
qsmxt/interfaces/nipype_interface_addtojson.py
qsmxt/interfaces/nipype_interface_analyse.py
qsmxt/interfaces/nipype_interface_axialsampling.py
qsmxt/interfaces/nipype_interface_bet2.py
qsmxt/interfaces/nipype_interface_clearswi.py
qsmxt/interfaces/nipype_interface_combinemagnitude.py
qsmxt/interfaces/nipype_interface_copy_json_sidecar.py
qsmxt/interfaces/nipype_interface_copyfile.py
qsmxt/interfaces/nipype_interface_create_reference_dicom.py
qsmxt/interfaces/nipype_interface_erode.py
qsmxt/interfaces/nipype_interface_fastsurfer.py
qsmxt/interfaces/nipype_interface_hdbet.py
qsmxt/interfaces/nipype_interface_json.py
qsmxt/interfaces/nipype_interface_laplacian_unwrapping.py
qsmxt/interfaces/nipype_interface_makehomogeneous.py
qsmxt/interfaces/nipype_interface_masking.py
qsmxt/interfaces/nipype_interface_mgz2nii.py
qsmxt/interfaces/nipype_interface_nextqsm.py
qsmxt/interfaces/nipype_interface_nii2dcm.py
qsmxt/interfaces/nipype_interface_nonzeroaverage.py
qsmxt/interfaces/nipype_interface_phaseweights.py
qsmxt/interfaces/nipype_interface_processphase.py
qsmxt/interfaces/nipype_interface_qsm_referencing.py
qsmxt/interfaces/nipype_interface_qsmjl.py
qsmxt/interfaces/nipype_interface_resample_like.py
qsmxt/interfaces/nipype_interface_romeo.py
qsmxt/interfaces/nipype_interface_t2star_r2star.py
qsmxt/interfaces/nipype_interface_tgv_qsm.py
qsmxt/interfaces/nipype_interface_tgv_qsm_jl.py
qsmxt/interfaces/nipype_interface_twopass.py
qsmxt/interfaces/utils.py
qsmxt/scripts/__init__.py
qsmxt/scripts/antsBuildTemplate.py
qsmxt/scripts/hagberg_pb_masking.jl
qsmxt/scripts/logger.py
qsmxt/scripts/makehomogeneous.jl
qsmxt/scripts/mcpc3ds.jl
qsmxt/scripts/mrt_clearswi.jl
qsmxt/scripts/mrt_laplacian_unwrapping.jl
qsmxt/scripts/mrt_phase_weights.jl
qsmxt-8.2.2.dist-info/licenses/LICENSE
qsmxt-8.2.2.dist-info/METADATA
qsmxt-8.2.2.dist-info/WHEEL
qsmxt-8.2.2.dist-info/entry_points.txt
qsmxt-8.2.2.dist-info/top_level.txt
qsmxt-8.2.2.dist-info/RECORD
