Metadata-Version: 2.4
Name: qsmxt
Version: 8.2.2
License-File: LICENSE
Requires-Dist: psutil==6.1.0
Requires-Dist: datetime==5.5
Requires-Dist: networkx==2.8.8
Requires-Dist: numpy==1.24.3
Requires-Dist: h5py==3.11.0
Requires-Dist: nibabel==5.2.1
Requires-Dist: nilearn==0.10.4
Requires-Dist: traits==6.3.2
Requires-Dist: nipype==1.8.6
Requires-Dist: scipy==1.10.1
Requires-Dist: scikit-image==0.21.0
Requires-Dist: pydicom==2.4.4
Requires-Dist: seaborn==0.13.2
Requires-Dist: webdavclient3==3.14.6
Requires-Dist: images-upload-cli==1.1.3
Requires-Dist: qsm-forward==0.22
Requires-Dist: osfclient==0.0.5
Requires-Dist: niflow-nipype1-workflows==0.0.5
Requires-Dist: tensorflow==2.13.1
Requires-Dist: packaging==24.1
Requires-Dist: nextqsm==1.0.4
Requires-Dist: matplotlib==3.7.5
Requires-Dist: pandas==2.0.3
Requires-Dist: dicompare==0.1.41
Provides-Extra: dev
Requires-Dist: pytest>=7.0.0; extra == "dev"
Requires-Dist: pytest-mock>=3.10.0; extra == "dev"
Requires-Dist: pytest-cov>=4.0.0; extra == "dev"
Requires-Dist: pytest-xdist>=3.0.0; extra == "dev"
Requires-Dist: black>=22.0.0; extra == "dev"
Requires-Dist: isort>=5.10.0; extra == "dev"
Requires-Dist: flake8>=5.0.0; extra == "dev"
Provides-Extra: test
Requires-Dist: pytest>=7.0.0; extra == "test"
Requires-Dist: pytest-mock>=3.10.0; extra == "test"
Requires-Dist: pytest-cov>=4.0.0; extra == "test"
Requires-Dist: pytest-xdist>=3.0.0; extra == "test"
Requires-Dist: boutiques>=0.5.26; extra == "test"
Dynamic: description
Dynamic: license-file
Dynamic: provides-extra
Dynamic: requires-dist
